qmc5883l.py
circuitpython_qmc5883l-0.1.3.dist-info/LICENSE
circuitpython_qmc5883l-0.1.3.dist-info/METADATA
circuitpython_qmc5883l-0.1.3.dist-info/WHEEL
circuitpython_qmc5883l-0.1.3.dist-info/top_level.txt
circuitpython_qmc5883l-0.1.3.dist-info/RECORD
