Metadata-Version: 2.1
Name: circuitpython-qmc5883l
Version: 0.1.3
Summary: CircuitPython driver for the qmc5883l magnetometer
Author-email: "Jose D. Montoya" <qmc@mailmeto.mozmail.com>
License: MIT
Project-URL: Homepage, https://github.com/jposada202020/CircuitPython_qmc5883l
Keywords: adafruit,blinka,circuitpython,micropython,qmc5883l,magnetometer,driver,sensor,qmc5883l
Classifier: Intended Audience :: Developers
Classifier: Topic :: Software Development :: Libraries
Classifier: Topic :: Software Development :: Embedded Systems
Classifier: Topic :: System :: Hardware
Classifier: License :: OSI Approved :: MIT License
Classifier: Programming Language :: Python :: 3
Provides-Extra: optional
License-File: LICENSE
